{
  "pokemon": [
    {
      "name": "sandshrew-alola",
      "dex_id": 27,
      "weight": 400,
      "height": 7,
      "exp_yield": 60,
      "abilities": [
        {
          "ability": {
            "name": "snow-cloak"
          }
        },
        {
          "ability": {
            "name": "slush-rush"
          }
        }
      ],
      "types": [
        {
          "type": {
            "name": "ice"
          }
        },
        {
          "type": {
            "name": "steel"
          }
        }
      ],
      "stats": [
        {
          "base_stat": 50,
          "stat": {
            "name": "hp"
          }
        },
        {
          "base_stat": 75,
          "stat": {
            "name": "attack"
          }
        },
        {
          "base_stat": 90,
          "stat": {
            "name": "defense"
          }
        },
        {
          "base_stat": 10,
          "stat": {
            "name": "special-attack"
          }
        },
        {
          "base_stat": 35,
          "stat": {
            "name": "special-defense"
          }
        },
        {
          "base_stat": 40,
          "stat": {
            "name": "speed"
          }
        }
      ],
      "levelUpMoves": [
        {
          "move": {
            "name": "scratch",
            "power": 40,
            "type": {
              "name": "normal"
            },
            "category": {
              "name": "physical"
            }
          },
          "level": 1
        },
        {
          "move": {
            "name": "defense-curl",
            "power": null,
            "type": {
              "name": "normal"
            },
            "category": {
              "name": "status"
            }
          },
          "level": 1
        },
        {
          "move": {
            "name": "bide",
            "power": null,
            "type": {
              "name": "normal"
            },
            "category": {
              "name": "physical"
            }
          },
          "level": 3
        },
        {
          "move": {
            "name": "powder-snow",
            "power": 40,
            "type": {
              "name": "ice"
            },
            "category": {
              "name": "special"
            }
          },
          "level": 5
        },
        {
          "move": {
            "name": "ice-ball",
            "power": 30,
            "type": {
              "name": "ice"
            },
            "category": {
              "name": "physical"
            }
          },
          "level": 7
        },
        {
          "move": {
            "name": "rapid-spin",
            "power": 50,
            "type": {
              "name": "normal"
            },
            "category": {
              "name": "physical"
            }
          },
          "level": 9
        },
        {
          "move": {
            "name": "fury-cutter",
            "power": 40,
            "type": {
              "name": "bug"
            },
            "category": {
              "name": "physical"
            }
          },
          "level": 11
        },
        {
          "move": {
            "name": "metal-claw",
            "power": 50,
            "type": {
              "name": "steel"
            },
            "category": {
              "name": "physical"
            }
          },
          "level": 14
        },
        {
          "move": {
            "name": "swift",
            "power": 60,
            "type": {
              "name": "normal"
            },
            "category": {
              "name": "special"
            }
          },
          "level": 17
        },
        {
          "move": {
            "name": "fury-swipes",
            "power": 18,
            "type": {
              "name": "normal"
            },
            "category": {
              "name": "physical"
            }
          },
          "level": 20
        },
        {
          "move": {
            "name": "iron-defense",
            "power": null,
            "type": {
              "name": "steel"
            },
            "category": {
              "name": "status"
            }
          },
          "level": 23
        },
        {
          "move": {
            "name": "slash",
            "power": 70,
            "type": {
              "name": "normal"
            },
            "category": {
              "name": "physical"
            }
          },
          "level": 26
        },
        {
          "move": {
            "name": "iron-head",
            "power": 80,
            "type": {
              "name": "steel"
            },
            "category": {
              "name": "physical"
            }
          },
          "level": 30
        },
        {
          "move": {
            "name": "gyro-ball",
            "power": null,
            "type": {
              "name": "steel"
            },
            "category": {
              "name": "physical"
            }
          },
          "level": 34
        },
        {
          "move": {
            "name": "swords-dance",
            "power": null,
            "type": {
              "name": "normal"
            },
            "category": {
              "name": "status"
            }
          },
          "level": 38
        },
        {
          "move": {
            "name": "hail",
            "power": null,
            "type": {
              "name": "ice"
            },
            "category": {
              "name": "status"
            }
          },
          "level": 42
        },
        {
          "move": {
            "name": "blizzard",
            "power": 110,
            "type": {
              "name": "ice"
            },
            "category": {
              "name": "special"
            }
          },
          "level": 46
        }
      ],
      "machineMoves": [
        {
          "move": {
            "name": "swords-dance",
            "power": null,
            "type": {
              "name": "normal"
            },
            "category": {
              "name": "status"
            }
          }
        },
        {
          "move": {
            "name": "blizzard",
            "power": 110,
            "type": {
              "name": "ice"
            },
            "category": {
              "name": "special"
            }
          }
        },
        {
          "move": {
            "name": "earthquake",
            "power": 100,
            "type": {
              "name": "ground"
            },
            "category": {
              "name": "physical"
            }
          }
        },
        {
          "move": {
            "name": "toxic",
            "power": null,
            "type": {
              "name": "poison"
            },
            "category": {
              "name": "status"
            }
          }
        },
        {
          "move": {
            "name": "double-team",
            "power": null,
            "type": {
              "name": "normal"
            },
            "category": {
              "name": "status"
            }
          }
        },
        {
          "move": {
            "name": "leech-life",
            "power": 80,
            "type": {
              "name": "bug"
            },
            "category": {
              "name": "physical"
            }
          }
        },
        {
          "move": {
            "name": "rest",
            "power": null,
            "type": {
              "name": "psychic"
            },
            "category": {
              "name": "status"
            }
          }
        },
        {
          "move": {
            "name": "rock-slide",
            "power": 75,
            "type": {
              "name": "rock"
            },
            "category": {
              "name": "physical"
            }
          }
        },
        {
          "move": {
            "name": "substitute",
            "power": null,
            "type": {
              "name": "normal"
            },
            "category": {
              "name": "status"
            }
          }
        },
        {
          "move": {
            "name": "thief",
            "power": 60,
            "type": {
              "name": "dark"
            },
            "category": {
              "name": "physical"
            }
          }
        },
        {
          "move": {
            "name": "protect",
            "power": null,
            "type": {
              "name": "normal"
            },
            "category": {
              "name": "status"
            }
          }
        },
        {
          "move": {
            "name": "swagger",
            "power": null,
            "type": {
              "name": "normal"
            },
            "category": {
              "name": "status"
            }
          }
        },
        {
          "move": {
            "name": "attract",
            "power": null,
            "type": {
              "name": "normal"
            },
            "category": {
              "name": "status"
            }
          }
        },
        {
          "move": {
            "name": "sleep-talk",
            "power": null,
            "type": {
              "name": "normal"
            },
            "category": {
              "name": "status"
            }
          }
        },
        {
          "move": {
            "name": "return",
            "power": null,
            "type": {
              "name": "normal"
            },
            "category": {
              "name": "physical"
            }
          }
        },
        {
          "move": {
            "name": "frustration",
            "power": null,
            "type": {
              "name": "normal"
            },
            "category": {
              "name": "physical"
            }
          }
        },
        {
          "move": {
            "name": "safeguard",
            "power": null,
            "type": {
              "name": "normal"
            },
            "category": {
              "name": "status"
            }
          }
        },
        {
          "move": {
            "name": "hidden-power",
            "power": 60,
            "type": {
              "name": "normal"
            },
            "category": {
              "name": "special"
            }
          }
        },
        {
          "move": {
            "name": "sunny-day",
            "power": null,
            "type": {
              "name": "fire"
            },
            "category": {
              "name": "status"
            }
          }
        },
        {
          "move": {
            "name": "hail",
            "power": null,
            "type": {
              "name": "ice"
            },
            "category": {
              "name": "status"
            }
          }
        },
        {
          "move": {
            "name": "facade",
            "power": 70,
            "type": {
              "name": "normal"
            },
            "category": {
              "name": "physical"
            }
          }
        },
        {
          "move": {
            "name": "brick-break",
            "power": 75,
            "type": {
              "name": "fighting"
            },
            "category": {
              "name": "physical"
            }
          }
        },
        {
          "move": {
            "name": "aerial-ace",
            "power": 60,
            "type": {
              "name": "flying"
            },
            "category": {
              "name": "physical"
            }
          }
        },
        {
          "move": {
            "name": "gyro-ball",
            "power": null,
            "type": {
              "name": "steel"
            },
            "category": {
              "name": "physical"
            }
          }
        },
        {
          "move": {
            "name": "fling",
            "power": null,
            "type": {
              "name": "dark"
            },
            "category": {
              "name": "physical"
            }
          }
        },
        {
          "move": {
            "name": "poison-jab",
            "power": 80,
            "type": {
              "name": "poison"
            },
            "category": {
              "name": "physical"
            }
          }
        },
        {
          "move": {
            "name": "x-scissor",
            "power": 80,
            "type": {
              "name": "bug"
            },
            "category": {
              "name": "physical"
            }
          }
        },
        {
          "move": {
            "name": "shadow-claw",
            "power": 70,
            "type": {
              "name": "ghost"
            },
            "category": {
              "name": "physical"
            }
          }
        },
        {
          "move": {
            "name": "round",
            "power": 60,
            "type": {
              "name": "normal"
            },
            "category": {
              "name": "special"
            }
          }
        },
        {
          "move": {
            "name": "bulldoze",
            "power": 60,
            "type": {
              "name": "ground"
            },
            "category": {
              "name": "physical"
            }
          }
        },
        {
          "move": {
            "name": "frost-breath",
            "power": 60,
            "type": {
              "name": "ice"
            },
            "category": {
              "name": "special"
            }
          }
        },
        {
          "move": {
            "name": "work-up",
            "power": null,
            "type": {
              "name": "normal"
            },
            "category": {
              "name": "status"
            }
          }
        },
        {
          "move": {
            "name": "confide",
            "power": null,
            "type": {
              "name": "normal"
            },
            "category": {
              "name": "status"
            }
          }
        },
        {
          "move": {
            "name": "aurora-veil",
            "power": null,
            "type": {
              "name": "ice"
            },
            "category": {
              "name": "status"
            }
          }
        }
      ],
      "eggMoves": [
        {
          "move": {
            "name": "ice-punch",
            "power": 75,
            "type": {
              "name": "ice"
            },
            "category": {
              "name": "physical"
            }
          }
        },
        {
          "move": {
            "name": "super-fang",
            "power": null,
            "type": {
              "name": "normal"
            },
            "category": {
              "name": "physical"
            }
          }
        },
        {
          "move": {
            "name": "snore",
            "power": 50,
            "type": {
              "name": "normal"
            },
            "category": {
              "name": "special"
            }
          }
        },
        {
          "move": {
            "name": "icy-wind",
            "power": 55,
            "type": {
              "name": "ice"
            },
            "category": {
              "name": "special"
            }
          }
        },
        {
          "move": {
            "name": "iron-tail",
            "power": 100,
            "type": {
              "name": "steel"
            },
            "category": {
              "name": "physical"
            }
          }
        },
        {
          "move": {
            "name": "focus-punch",
            "power": 150,
            "type": {
              "name": "fighting"
            },
            "category": {
              "name": "physical"
            }
          }
        },
        {
          "move": {
            "name": "knock-off",
            "power": 65,
            "type": {
              "name": "dark"
            },
            "category": {
              "name": "physical"
            }
          }
        },
        {
          "move": {
            "name": "iron-defense",
            "power": null,
            "type": {
              "name": "steel"
            },
            "category": {
              "name": "status"
            }
          }
        },
        {
          "move": {
            "name": "covet",
            "power": 60,
            "type": {
              "name": "normal"
            },
            "category": {
              "name": "physical"
            }
          }
        },
        {
          "move": {
            "name": "aqua-tail",
            "power": 90,
            "type": {
              "name": "water"
            },
            "category": {
              "name": "physical"
            }
          }
        },
        {
          "move": {
            "name": "iron-head",
            "power": 80,
            "type": {
              "name": "steel"
            },
            "category": {
              "name": "physical"
            }
          }
        },
        {
          "move": {
            "name": "stealth-rock",
            "power": null,
            "type": {
              "name": "rock"
            },
            "category": {
              "name": "status"
            }
          }
        },
        {
          "move": {
            "name": "throat-chop",
            "power": 80,
            "type": {
              "name": "dark"
            },
            "category": {
              "name": "physical"
            }
          }
        }
      ],
      "specy": {
        "evolution_chain": {
          "id": 11,
          "species": [
            {
              "name": "sandshrew",
              "pre_evolution": null,
              "evolution_condition": []
            },
            {
              "name": "sandslash",
              "pre_evolution": 27,
              "evolution_condition": [
                {
                  "level": 22,
                  "iq": null,
                  "item": null,
                  "held_item": null,
                  "trigger": 1,
                  "time": ""
                },
                {
                  "level": null,
                  "iq": null,
                  "item": 885,
                  "held_item": null,
                  "trigger": 3,
                  "time": ""
                }
              ]
            }
          ]
        },
        "category": [
          {
            "genus": "Mouse Pokémon"
          }
        ]
      }
    }
  ]
}