{
  "pokemon": [
    {
      "name": "araquanid-totem",
      "dex_id": 752,
      "weight": 2175,
      "height": 31,
      "exp_yield": 159,
      "abilities": [
        {
          "ability": {
            "name": "water-bubble"
          }
        },
        {
          "ability": {
            "name": "water-absorb"
          }
        }
      ],
      "types": [
        {
          "type": {
            "name": "water"
          }
        },
        {
          "type": {
            "name": "bug"
          }
        }
      ],
      "stats": [
        {
          "base_stat": 68,
          "stat": {
            "name": "hp"
          }
        },
        {
          "base_stat": 70,
          "stat": {
            "name": "attack"
          }
        },
        {
          "base_stat": 92,
          "stat": {
            "name": "defense"
          }
        },
        {
          "base_stat": 50,
          "stat": {
            "name": "special-attack"
          }
        },
        {
          "base_stat": 132,
          "stat": {
            "name": "special-defense"
          }
        },
        {
          "base_stat": 42,
          "stat": {
            "name": "speed"
          }
        }
      ],
      "levelUpMoves": [
        {
          "move": {
            "name": "bubble",
            "power": 40,
            "type": {
              "name": "water"
            },
            "category": {
              "name": "special"
            }
          },
          "level": 1
        },
        {
          "move": {
            "name": "spider-web",
            "power": null,
            "type": {
              "name": "bug"
            },
            "category": {
              "name": "status"
            }
          },
          "level": 1
        },
        {
          "move": {
            "name": "bug-bite",
            "power": 60,
            "type": {
              "name": "bug"
            },
            "category": {
              "name": "physical"
            }
          },
          "level": 1
        },
        {
          "move": {
            "name": "wide-guard",
            "power": null,
            "type": {
              "name": "rock"
            },
            "category": {
              "name": "status"
            }
          },
          "level": 1
        },
        {
          "move": {
            "name": "soak",
            "power": null,
            "type": {
              "name": "water"
            },
            "category": {
              "name": "status"
            }
          },
          "level": 1
        },
        {
          "move": {
            "name": "infestation",
            "power": 20,
            "type": {
              "name": "bug"
            },
            "category": {
              "name": "special"
            }
          },
          "level": 1
        },
        {
          "move": {
            "name": "infestation",
            "power": 20,
            "type": {
              "name": "bug"
            },
            "category": {
              "name": "special"
            }
          },
          "level": 5
        },
        {
          "move": {
            "name": "spider-web",
            "power": null,
            "type": {
              "name": "bug"
            },
            "category": {
              "name": "status"
            }
          },
          "level": 8
        },
        {
          "move": {
            "name": "bug-bite",
            "power": 60,
            "type": {
              "name": "bug"
            },
            "category": {
              "name": "physical"
            }
          },
          "level": 13
        },
        {
          "move": {
            "name": "bubble-beam",
            "power": 65,
            "type": {
              "name": "water"
            },
            "category": {
              "name": "special"
            }
          },
          "level": 16
        },
        {
          "move": {
            "name": "bite",
            "power": 60,
            "type": {
              "name": "dark"
            },
            "category": {
              "name": "physical"
            }
          },
          "level": 21
        },
        {
          "move": {
            "name": "aqua-ring",
            "power": null,
            "type": {
              "name": "water"
            },
            "category": {
              "name": "status"
            }
          },
          "level": 26
        },
        {
          "move": {
            "name": "leech-life",
            "power": 80,
            "type": {
              "name": "bug"
            },
            "category": {
              "name": "physical"
            }
          },
          "level": 33
        },
        {
          "move": {
            "name": "crunch",
            "power": 80,
            "type": {
              "name": "dark"
            },
            "category": {
              "name": "physical"
            }
          },
          "level": 38
        },
        {
          "move": {
            "name": "lunge",
            "power": 80,
            "type": {
              "name": "bug"
            },
            "category": {
              "name": "physical"
            }
          },
          "level": 45
        },
        {
          "move": {
            "name": "mirror-coat",
            "power": null,
            "type": {
              "name": "psychic"
            },
            "category": {
              "name": "special"
            }
          },
          "level": 50
        },
        {
          "move": {
            "name": "liquidation",
            "power": 85,
            "type": {
              "name": "water"
            },
            "category": {
              "name": "physical"
            }
          },
          "level": 57
        },
        {
          "move": {
            "name": "entrainment",
            "power": null,
            "type": {
              "name": "normal"
            },
            "category": {
              "name": "status"
            }
          },
          "level": 62
        }
      ],
      "machineMoves": [
        {
          "move": {
            "name": "surf",
            "power": 90,
            "type": {
              "name": "water"
            },
            "category": {
              "name": "special"
            }
          }
        },
        {
          "move": {
            "name": "ice-beam",
            "power": 90,
            "type": {
              "name": "ice"
            },
            "category": {
              "name": "special"
            }
          }
        },
        {
          "move": {
            "name": "blizzard",
            "power": 110,
            "type": {
              "name": "ice"
            },
            "category": {
              "name": "special"
            }
          }
        },
        {
          "move": {
            "name": "toxic",
            "power": null,
            "type": {
              "name": "poison"
            },
            "category": {
              "name": "status"
            }
          }
        },
        {
          "move": {
            "name": "double-team",
            "power": null,
            "type": {
              "name": "normal"
            },
            "category": {
              "name": "status"
            }
          }
        },
        {
          "move": {
            "name": "reflect",
            "power": null,
            "type": {
              "name": "psychic"
            },
            "category": {
              "name": "status"
            }
          }
        },
        {
          "move": {
            "name": "waterfall",
            "power": 80,
            "type": {
              "name": "water"
            },
            "category": {
              "name": "physical"
            }
          }
        },
        {
          "move": {
            "name": "leech-life",
            "power": 80,
            "type": {
              "name": "bug"
            },
            "category": {
              "name": "physical"
            }
          }
        },
        {
          "move": {
            "name": "rest",
            "power": null,
            "type": {
              "name": "psychic"
            },
            "category": {
              "name": "status"
            }
          }
        },
        {
          "move": {
            "name": "substitute",
            "power": null,
            "type": {
              "name": "normal"
            },
            "category": {
              "name": "status"
            }
          }
        },
        {
          "move": {
            "name": "protect",
            "power": null,
            "type": {
              "name": "normal"
            },
            "category": {
              "name": "status"
            }
          }
        },
        {
          "move": {
            "name": "swagger",
            "power": null,
            "type": {
              "name": "normal"
            },
            "category": {
              "name": "status"
            }
          }
        },
        {
          "move": {
            "name": "attract",
            "power": null,
            "type": {
              "name": "normal"
            },
            "category": {
              "name": "status"
            }
          }
        },
        {
          "move": {
            "name": "sleep-talk",
            "power": null,
            "type": {
              "name": "normal"
            },
            "category": {
              "name": "status"
            }
          }
        },
        {
          "move": {
            "name": "return",
            "power": null,
            "type": {
              "name": "normal"
            },
            "category": {
              "name": "physical"
            }
          }
        },
        {
          "move": {
            "name": "frustration",
            "power": null,
            "type": {
              "name": "normal"
            },
            "category": {
              "name": "physical"
            }
          }
        },
        {
          "move": {
            "name": "safeguard",
            "power": null,
            "type": {
              "name": "normal"
            },
            "category": {
              "name": "status"
            }
          }
        },
        {
          "move": {
            "name": "hidden-power",
            "power": 60,
            "type": {
              "name": "normal"
            },
            "category": {
              "name": "special"
            }
          }
        },
        {
          "move": {
            "name": "rain-dance",
            "power": null,
            "type": {
              "name": "water"
            },
            "category": {
              "name": "status"
            }
          }
        },
        {
          "move": {
            "name": "facade",
            "power": 70,
            "type": {
              "name": "normal"
            },
            "category": {
              "name": "physical"
            }
          }
        },
        {
          "move": {
            "name": "poison-jab",
            "power": 80,
            "type": {
              "name": "poison"
            },
            "category": {
              "name": "physical"
            }
          }
        },
        {
          "move": {
            "name": "x-scissor",
            "power": 80,
            "type": {
              "name": "bug"
            },
            "category": {
              "name": "physical"
            }
          }
        },
        {
          "move": {
            "name": "round",
            "power": 60,
            "type": {
              "name": "normal"
            },
            "category": {
              "name": "special"
            }
          }
        },
        {
          "move": {
            "name": "scald",
            "power": 80,
            "type": {
              "name": "water"
            },
            "category": {
              "name": "special"
            }
          }
        },
        {
          "move": {
            "name": "frost-breath",
            "power": 60,
            "type": {
              "name": "ice"
            },
            "category": {
              "name": "special"
            }
          }
        },
        {
          "move": {
            "name": "confide",
            "power": null,
            "type": {
              "name": "normal"
            },
            "category": {
              "name": "status"
            }
          }
        },
        {
          "move": {
            "name": "infestation",
            "power": 20,
            "type": {
              "name": "bug"
            },
            "category": {
              "name": "special"
            }
          }
        }
      ],
      "eggMoves": [
        {
          "move": {
            "name": "snore",
            "power": 50,
            "type": {
              "name": "normal"
            },
            "category": {
              "name": "special"
            }
          }
        },
        {
          "move": {
            "name": "icy-wind",
            "power": 55,
            "type": {
              "name": "ice"
            },
            "category": {
              "name": "special"
            }
          }
        },
        {
          "move": {
            "name": "giga-drain",
            "power": 75,
            "type": {
              "name": "grass"
            },
            "category": {
              "name": "special"
            }
          }
        },
        {
          "move": {
            "name": "magic-coat",
            "power": null,
            "type": {
              "name": "psychic"
            },
            "category": {
              "name": "status"
            }
          }
        },
        {
          "move": {
            "name": "signal-beam",
            "power": 75,
            "type": {
              "name": "bug"
            },
            "category": {
              "name": "special"
            }
          }
        },
        {
          "move": {
            "name": "iron-defense",
            "power": null,
            "type": {
              "name": "steel"
            },
            "category": {
              "name": "status"
            }
          }
        },
        {
          "move": {
            "name": "water-pulse",
            "power": 60,
            "type": {
              "name": "water"
            },
            "category": {
              "name": "special"
            }
          }
        },
        {
          "move": {
            "name": "bug-bite",
            "power": 60,
            "type": {
              "name": "bug"
            },
            "category": {
              "name": "physical"
            }
          }
        },
        {
          "move": {
            "name": "wonder-room",
            "power": null,
            "type": {
              "name": "psychic"
            },
            "category": {
              "name": "status"
            }
          }
        },
        {
          "move": {
            "name": "magic-room",
            "power": null,
            "type": {
              "name": "psychic"
            },
            "category": {
              "name": "status"
            }
          }
        },
        {
          "move": {
            "name": "laser-focus",
            "power": null,
            "type": {
              "name": "normal"
            },
            "category": {
              "name": "status"
            }
          }
        },
        {
          "move": {
            "name": "liquidation",
            "power": 85,
            "type": {
              "name": "water"
            },
            "category": {
              "name": "physical"
            }
          }
        }
      ],
      "specy": {
        "evolution_chain": {
          "id": 387,
          "species": [
            {
              "name": "dewpider",
              "pre_evolution": null,
              "evolution_condition": []
            },
            {
              "name": "araquanid",
              "pre_evolution": 751,
              "evolution_condition": [
                {
                  "level": 22,
                  "iq": null,
                  "item": null,
                  "held_item": null,
                  "trigger": 1,
                  "time": ""
                }
              ]
            }
          ]
        },
        "category": [
          {
            "genus": "Water Bubble Pokémon"
          }
        ]
      }
    }
  ]
}