{
  "pokemon": [
    {
      "name": "spoink",
      "dex_id": 325,
      "weight": 306,
      "height": 7,
      "exp_yield": 66,
      "abilities": [
        {
          "ability": {
            "name": "thick-fat"
          }
        },
        {
          "ability": {
            "name": "own-tempo"
          }
        },
        {
          "ability": {
            "name": "gluttony"
          }
        }
      ],
      "types": [
        {
          "type": {
            "name": "psychic"
          }
        }
      ],
      "stats": [
        {
          "base_stat": 60,
          "stat": {
            "name": "hp"
          }
        },
        {
          "base_stat": 25,
          "stat": {
            "name": "attack"
          }
        },
        {
          "base_stat": 35,
          "stat": {
            "name": "defense"
          }
        },
        {
          "base_stat": 70,
          "stat": {
            "name": "special-attack"
          }
        },
        {
          "base_stat": 80,
          "stat": {
            "name": "special-defense"
          }
        },
        {
          "base_stat": 60,
          "stat": {
            "name": "speed"
          }
        }
      ],
      "levelUpMoves": [
        {
          "move": {
            "name": "splash",
            "power": null,
            "type": {
              "name": "normal"
            },
            "category": {
              "name": "status"
            }
          },
          "level": 1
        },
        {
          "move": {
            "name": "psywave",
            "power": null,
            "type": {
              "name": "psychic"
            },
            "category": {
              "name": "special"
            }
          },
          "level": 7
        },
        {
          "move": {
            "name": "odor-sleuth",
            "power": null,
            "type": {
              "name": "normal"
            },
            "category": {
              "name": "status"
            }
          },
          "level": 10
        },
        {
          "move": {
            "name": "psybeam",
            "power": 65,
            "type": {
              "name": "psychic"
            },
            "category": {
              "name": "special"
            }
          },
          "level": 14
        },
        {
          "move": {
            "name": "psych-up",
            "power": null,
            "type": {
              "name": "normal"
            },
            "category": {
              "name": "status"
            }
          },
          "level": 15
        },
        {
          "move": {
            "name": "confuse-ray",
            "power": null,
            "type": {
              "name": "ghost"
            },
            "category": {
              "name": "status"
            }
          },
          "level": 18
        },
        {
          "move": {
            "name": "magic-coat",
            "power": null,
            "type": {
              "name": "psychic"
            },
            "category": {
              "name": "status"
            }
          },
          "level": 21
        },
        {
          "move": {
            "name": "zen-headbutt",
            "power": 80,
            "type": {
              "name": "psychic"
            },
            "category": {
              "name": "physical"
            }
          },
          "level": 26
        },
        {
          "move": {
            "name": "rest",
            "power": null,
            "type": {
              "name": "psychic"
            },
            "category": {
              "name": "status"
            }
          },
          "level": 29
        },
        {
          "move": {
            "name": "snore",
            "power": 50,
            "type": {
              "name": "normal"
            },
            "category": {
              "name": "special"
            }
          },
          "level": 29
        },
        {
          "move": {
            "name": "payback",
            "power": 50,
            "type": {
              "name": "dark"
            },
            "category": {
              "name": "physical"
            }
          },
          "level": 34
        },
        {
          "move": {
            "name": "psychic",
            "power": 90,
            "type": {
              "name": "psychic"
            },
            "category": {
              "name": "special"
            }
          },
          "level": 41
        },
        {
          "move": {
            "name": "power-gem",
            "power": 80,
            "type": {
              "name": "rock"
            },
            "category": {
              "name": "special"
            }
          },
          "level": 46
        },
        {
          "move": {
            "name": "bounce",
            "power": 85,
            "type": {
              "name": "flying"
            },
            "category": {
              "name": "physical"
            }
          },
          "level": 48
        }
      ],
      "machineMoves": [
        {
          "move": {
            "name": "thunder-wave",
            "power": null,
            "type": {
              "name": "electric"
            },
            "category": {
              "name": "status"
            }
          }
        },
        {
          "move": {
            "name": "toxic",
            "power": null,
            "type": {
              "name": "poison"
            },
            "category": {
              "name": "status"
            }
          }
        },
        {
          "move": {
            "name": "psychic",
            "power": 90,
            "type": {
              "name": "psychic"
            },
            "category": {
              "name": "special"
            }
          }
        },
        {
          "move": {
            "name": "double-team",
            "power": null,
            "type": {
              "name": "normal"
            },
            "category": {
              "name": "status"
            }
          }
        },
        {
          "move": {
            "name": "light-screen",
            "power": null,
            "type": {
              "name": "psychic"
            },
            "category": {
              "name": "status"
            }
          }
        },
        {
          "move": {
            "name": "reflect",
            "power": null,
            "type": {
              "name": "psychic"
            },
            "category": {
              "name": "status"
            }
          }
        },
        {
          "move": {
            "name": "dream-eater",
            "power": 100,
            "type": {
              "name": "psychic"
            },
            "category": {
              "name": "special"
            }
          }
        },
        {
          "move": {
            "name": "flash",
            "power": null,
            "type": {
              "name": "normal"
            },
            "category": {
              "name": "status"
            }
          }
        },
        {
          "move": {
            "name": "rest",
            "power": null,
            "type": {
              "name": "psychic"
            },
            "category": {
              "name": "status"
            }
          }
        },
        {
          "move": {
            "name": "substitute",
            "power": null,
            "type": {
              "name": "normal"
            },
            "category": {
              "name": "status"
            }
          }
        },
        {
          "move": {
            "name": "thief",
            "power": 60,
            "type": {
              "name": "dark"
            },
            "category": {
              "name": "physical"
            }
          }
        },
        {
          "move": {
            "name": "protect",
            "power": null,
            "type": {
              "name": "normal"
            },
            "category": {
              "name": "status"
            }
          }
        },
        {
          "move": {
            "name": "endure",
            "power": null,
            "type": {
              "name": "normal"
            },
            "category": {
              "name": "status"
            }
          }
        },
        {
          "move": {
            "name": "swagger",
            "power": null,
            "type": {
              "name": "normal"
            },
            "category": {
              "name": "status"
            }
          }
        },
        {
          "move": {
            "name": "attract",
            "power": null,
            "type": {
              "name": "normal"
            },
            "category": {
              "name": "status"
            }
          }
        },
        {
          "move": {
            "name": "sleep-talk",
            "power": null,
            "type": {
              "name": "normal"
            },
            "category": {
              "name": "status"
            }
          }
        },
        {
          "move": {
            "name": "return",
            "power": null,
            "type": {
              "name": "normal"
            },
            "category": {
              "name": "physical"
            }
          }
        },
        {
          "move": {
            "name": "frustration",
            "power": null,
            "type": {
              "name": "normal"
            },
            "category": {
              "name": "physical"
            }
          }
        },
        {
          "move": {
            "name": "iron-tail",
            "power": 100,
            "type": {
              "name": "steel"
            },
            "category": {
              "name": "physical"
            }
          }
        },
        {
          "move": {
            "name": "hidden-power",
            "power": 60,
            "type": {
              "name": "normal"
            },
            "category": {
              "name": "special"
            }
          }
        },
        {
          "move": {
            "name": "rain-dance",
            "power": null,
            "type": {
              "name": "water"
            },
            "category": {
              "name": "status"
            }
          }
        },
        {
          "move": {
            "name": "sunny-day",
            "power": null,
            "type": {
              "name": "fire"
            },
            "category": {
              "name": "status"
            }
          }
        },
        {
          "move": {
            "name": "psych-up",
            "power": null,
            "type": {
              "name": "normal"
            },
            "category": {
              "name": "status"
            }
          }
        },
        {
          "move": {
            "name": "shadow-ball",
            "power": 80,
            "type": {
              "name": "ghost"
            },
            "category": {
              "name": "special"
            }
          }
        },
        {
          "move": {
            "name": "torment",
            "power": null,
            "type": {
              "name": "dark"
            },
            "category": {
              "name": "status"
            }
          }
        },
        {
          "move": {
            "name": "facade",
            "power": 70,
            "type": {
              "name": "normal"
            },
            "category": {
              "name": "physical"
            }
          }
        },
        {
          "move": {
            "name": "taunt",
            "power": null,
            "type": {
              "name": "dark"
            },
            "category": {
              "name": "status"
            }
          }
        },
        {
          "move": {
            "name": "recycle",
            "power": null,
            "type": {
              "name": "normal"
            },
            "category": {
              "name": "status"
            }
          }
        },
        {
          "move": {
            "name": "skill-swap",
            "power": null,
            "type": {
              "name": "psychic"
            },
            "category": {
              "name": "status"
            }
          }
        },
        {
          "move": {
            "name": "snatch",
            "power": null,
            "type": {
              "name": "dark"
            },
            "category": {
              "name": "status"
            }
          }
        },
        {
          "move": {
            "name": "secret-power",
            "power": 70,
            "type": {
              "name": "normal"
            },
            "category": {
              "name": "physical"
            }
          }
        },
        {
          "move": {
            "name": "calm-mind",
            "power": null,
            "type": {
              "name": "psychic"
            },
            "category": {
              "name": "status"
            }
          }
        },
        {
          "move": {
            "name": "shock-wave",
            "power": 60,
            "type": {
              "name": "electric"
            },
            "category": {
              "name": "special"
            }
          }
        },
        {
          "move": {
            "name": "natural-gift",
            "power": null,
            "type": {
              "name": "normal"
            },
            "category": {
              "name": "physical"
            }
          }
        },
        {
          "move": {
            "name": "payback",
            "power": 50,
            "type": {
              "name": "dark"
            },
            "category": {
              "name": "physical"
            }
          }
        },
        {
          "move": {
            "name": "trick-room",
            "power": null,
            "type": {
              "name": "psychic"
            },
            "category": {
              "name": "status"
            }
          }
        },
        {
          "move": {
            "name": "captivate",
            "power": null,
            "type": {
              "name": "normal"
            },
            "category": {
              "name": "status"
            }
          }
        },
        {
          "move": {
            "name": "grass-knot",
            "power": null,
            "type": {
              "name": "grass"
            },
            "category": {
              "name": "special"
            }
          }
        },
        {
          "move": {
            "name": "charge-beam",
            "power": 50,
            "type": {
              "name": "electric"
            },
            "category": {
              "name": "special"
            }
          }
        }
      ],
      "eggMoves": [
        {
          "move": {
            "name": "swift",
            "power": 60,
            "type": {
              "name": "normal"
            },
            "category": {
              "name": "special"
            }
          }
        },
        {
          "move": {
            "name": "snore",
            "power": 50,
            "type": {
              "name": "normal"
            },
            "category": {
              "name": "special"
            }
          }
        },
        {
          "move": {
            "name": "icy-wind",
            "power": 55,
            "type": {
              "name": "ice"
            },
            "category": {
              "name": "special"
            }
          }
        },
        {
          "move": {
            "name": "trick",
            "power": null,
            "type": {
              "name": "psychic"
            },
            "category": {
              "name": "status"
            }
          }
        },
        {
          "move": {
            "name": "signal-beam",
            "power": 75,
            "type": {
              "name": "bug"
            },
            "category": {
              "name": "special"
            }
          }
        },
        {
          "move": {
            "name": "bounce",
            "power": 85,
            "type": {
              "name": "flying"
            },
            "category": {
              "name": "physical"
            }
          }
        },
        {
          "move": {
            "name": "zen-headbutt",
            "power": 80,
            "type": {
              "name": "psychic"
            },
            "category": {
              "name": "physical"
            }
          }
        }
      ],
      "specy": {
        "evolution_chain": {
          "id": 164,
          "species": [
            {
              "name": "spoink",
              "pre_evolution": null,
              "evolution_condition": []
            },
            {
              "name": "grumpig",
              "pre_evolution": 325,
              "evolution_condition": [
                {
                  "level": 32,
                  "iq": null,
                  "item": null,
                  "held_item": null,
                  "trigger": 1,
                  "time": ""
                }
              ]
            }
          ]
        },
        "category": [
          {
            "genus": "Bounce Pokémon"
          }
        ]
      }
    }
  ]
}