{
  "pokemon": [
    {
      "name": "beldum",
      "dex_id": 374,
      "weight": 952,
      "height": 6,
      "exp_yield": 60,
      "abilities": [
        {
          "ability": {
            "name": "clear-body"
          }
        },
        {
          "ability": {
            "name": "light-metal"
          }
        }
      ],
      "types": [
        {
          "type": {
            "name": "steel"
          }
        },
        {
          "type": {
            "name": "psychic"
          }
        }
      ],
      "stats": [
        {
          "base_stat": 40,
          "stat": {
            "name": "hp"
          }
        },
        {
          "base_stat": 55,
          "stat": {
            "name": "attack"
          }
        },
        {
          "base_stat": 80,
          "stat": {
            "name": "defense"
          }
        },
        {
          "base_stat": 35,
          "stat": {
            "name": "special-attack"
          }
        },
        {
          "base_stat": 60,
          "stat": {
            "name": "special-defense"
          }
        },
        {
          "base_stat": 30,
          "stat": {
            "name": "speed"
          }
        }
      ],
      "levelUpMoves": [
        {
          "move": {
            "name": "take-down",
            "power": 90,
            "type": {
              "name": "normal"
            },
            "category": {
              "name": "physical"
            }
          },
          "level": 1
        }
      ],
      "machineMoves": [],
      "eggMoves": [
        {
          "move": {
            "name": "iron-defense",
            "power": null,
            "type": {
              "name": "steel"
            },
            "category": {
              "name": "status"
            }
          }
        },
        {
          "move": {
            "name": "zen-headbutt",
            "power": 80,
            "type": {
              "name": "psychic"
            },
            "category": {
              "name": "physical"
            }
          }
        },
        {
          "move": {
            "name": "iron-head",
            "power": 80,
            "type": {
              "name": "steel"
            },
            "category": {
              "name": "physical"
            }
          }
        }
      ],
      "specy": {
        "evolution_chain": {
          "id": 192,
          "species": [
            {
              "name": "beldum",
              "pre_evolution": null,
              "evolution_condition": []
            },
            {
              "name": "metang",
              "pre_evolution": 374,
              "evolution_condition": [
                {
                  "level": 20,
                  "iq": null,
                  "item": null,
                  "held_item": null,
                  "trigger": 1,
                  "time": ""
                }
              ]
            },
            {
              "name": "metagross",
              "pre_evolution": 375,
              "evolution_condition": [
                {
                  "level": 45,
                  "iq": null,
                  "item": null,
                  "held_item": null,
                  "trigger": 1,
                  "time": ""
                }
              ]
            }
          ]
        },
        "category": [
          {
            "genus": "Iron Ball Pokémon"
          }
        ]
      }
    }
  ]
}