{
  "pokemon": [
    {
      "name": "munchlax",
      "dex_id": 446,
      "weight": 1050,
      "height": 6,
      "exp_yield": 78,
      "abilities": [
        {
          "ability": {
            "name": "pickup"
          }
        },
        {
          "ability": {
            "name": "thick-fat"
          }
        },
        {
          "ability": {
            "name": "gluttony"
          }
        }
      ],
      "types": [
        {
          "type": {
            "name": "normal"
          }
        }
      ],
      "stats": [
        {
          "base_stat": 135,
          "stat": {
            "name": "hp"
          }
        },
        {
          "base_stat": 85,
          "stat": {
            "name": "attack"
          }
        },
        {
          "base_stat": 40,
          "stat": {
            "name": "defense"
          }
        },
        {
          "base_stat": 40,
          "stat": {
            "name": "special-attack"
          }
        },
        {
          "base_stat": 85,
          "stat": {
            "name": "special-defense"
          }
        },
        {
          "base_stat": 5,
          "stat": {
            "name": "speed"
          }
        }
      ],
      "levelUpMoves": [
        {
          "move": {
            "name": "tackle",
            "power": 40,
            "type": {
              "name": "normal"
            },
            "category": {
              "name": "physical"
            }
          },
          "level": 1
        },
        {
          "move": {
            "name": "metronome",
            "power": null,
            "type": {
              "name": "normal"
            },
            "category": {
              "name": "status"
            }
          },
          "level": 1
        },
        {
          "move": {
            "name": "odor-sleuth",
            "power": null,
            "type": {
              "name": "normal"
            },
            "category": {
              "name": "status"
            }
          },
          "level": 1
        },
        {
          "move": {
            "name": "defense-curl",
            "power": null,
            "type": {
              "name": "normal"
            },
            "category": {
              "name": "status"
            }
          },
          "level": 4
        },
        {
          "move": {
            "name": "amnesia",
            "power": null,
            "type": {
              "name": "psychic"
            },
            "category": {
              "name": "status"
            }
          },
          "level": 9
        },
        {
          "move": {
            "name": "lick",
            "power": 30,
            "type": {
              "name": "ghost"
            },
            "category": {
              "name": "physical"
            }
          },
          "level": 12
        },
        {
          "move": {
            "name": "recycle",
            "power": null,
            "type": {
              "name": "normal"
            },
            "category": {
              "name": "status"
            }
          },
          "level": 17
        },
        {
          "move": {
            "name": "screech",
            "power": null,
            "type": {
              "name": "normal"
            },
            "category": {
              "name": "status"
            }
          },
          "level": 20
        },
        {
          "move": {
            "name": "stockpile",
            "power": null,
            "type": {
              "name": "normal"
            },
            "category": {
              "name": "status"
            }
          },
          "level": 25
        },
        {
          "move": {
            "name": "swallow",
            "power": null,
            "type": {
              "name": "normal"
            },
            "category": {
              "name": "status"
            }
          },
          "level": 28
        },
        {
          "move": {
            "name": "body-slam",
            "power": 85,
            "type": {
              "name": "normal"
            },
            "category": {
              "name": "physical"
            }
          },
          "level": 33
        },
        {
          "move": {
            "name": "fling",
            "power": null,
            "type": {
              "name": "dark"
            },
            "category": {
              "name": "physical"
            }
          },
          "level": 36
        },
        {
          "move": {
            "name": "rollout",
            "power": 30,
            "type": {
              "name": "rock"
            },
            "category": {
              "name": "physical"
            }
          },
          "level": 41
        },
        {
          "move": {
            "name": "natural-gift",
            "power": null,
            "type": {
              "name": "normal"
            },
            "category": {
              "name": "physical"
            }
          },
          "level": 44
        },
        {
          "move": {
            "name": "last-resort",
            "power": 140,
            "type": {
              "name": "normal"
            },
            "category": {
              "name": "physical"
            }
          },
          "level": 49
        }
      ],
      "machineMoves": [
        {
          "move": {
            "name": "flamethrower",
            "power": 90,
            "type": {
              "name": "fire"
            },
            "category": {
              "name": "special"
            }
          }
        },
        {
          "move": {
            "name": "surf",
            "power": 90,
            "type": {
              "name": "water"
            },
            "category": {
              "name": "special"
            }
          }
        },
        {
          "move": {
            "name": "ice-beam",
            "power": 90,
            "type": {
              "name": "ice"
            },
            "category": {
              "name": "special"
            }
          }
        },
        {
          "move": {
            "name": "blizzard",
            "power": 110,
            "type": {
              "name": "ice"
            },
            "category": {
              "name": "special"
            }
          }
        },
        {
          "move": {
            "name": "strength",
            "power": 80,
            "type": {
              "name": "normal"
            },
            "category": {
              "name": "physical"
            }
          }
        },
        {
          "move": {
            "name": "solar-beam",
            "power": 120,
            "type": {
              "name": "grass"
            },
            "category": {
              "name": "special"
            }
          }
        },
        {
          "move": {
            "name": "thunderbolt",
            "power": 90,
            "type": {
              "name": "electric"
            },
            "category": {
              "name": "special"
            }
          }
        },
        {
          "move": {
            "name": "thunder",
            "power": 110,
            "type": {
              "name": "electric"
            },
            "category": {
              "name": "special"
            }
          }
        },
        {
          "move": {
            "name": "earthquake",
            "power": 100,
            "type": {
              "name": "ground"
            },
            "category": {
              "name": "physical"
            }
          }
        },
        {
          "move": {
            "name": "toxic",
            "power": null,
            "type": {
              "name": "poison"
            },
            "category": {
              "name": "status"
            }
          }
        },
        {
          "move": {
            "name": "psychic",
            "power": 90,
            "type": {
              "name": "psychic"
            },
            "category": {
              "name": "special"
            }
          }
        },
        {
          "move": {
            "name": "double-team",
            "power": null,
            "type": {
              "name": "normal"
            },
            "category": {
              "name": "status"
            }
          }
        },
        {
          "move": {
            "name": "fire-blast",
            "power": 110,
            "type": {
              "name": "fire"
            },
            "category": {
              "name": "special"
            }
          }
        },
        {
          "move": {
            "name": "rest",
            "power": null,
            "type": {
              "name": "psychic"
            },
            "category": {
              "name": "status"
            }
          }
        },
        {
          "move": {
            "name": "rock-slide",
            "power": 75,
            "type": {
              "name": "rock"
            },
            "category": {
              "name": "physical"
            }
          }
        },
        {
          "move": {
            "name": "substitute",
            "power": null,
            "type": {
              "name": "normal"
            },
            "category": {
              "name": "status"
            }
          }
        },
        {
          "move": {
            "name": "protect",
            "power": null,
            "type": {
              "name": "normal"
            },
            "category": {
              "name": "status"
            }
          }
        },
        {
          "move": {
            "name": "sandstorm",
            "power": null,
            "type": {
              "name": "rock"
            },
            "category": {
              "name": "status"
            }
          }
        },
        {
          "move": {
            "name": "endure",
            "power": null,
            "type": {
              "name": "normal"
            },
            "category": {
              "name": "status"
            }
          }
        },
        {
          "move": {
            "name": "swagger",
            "power": null,
            "type": {
              "name": "normal"
            },
            "category": {
              "name": "status"
            }
          }
        },
        {
          "move": {
            "name": "attract",
            "power": null,
            "type": {
              "name": "normal"
            },
            "category": {
              "name": "status"
            }
          }
        },
        {
          "move": {
            "name": "sleep-talk",
            "power": null,
            "type": {
              "name": "normal"
            },
            "category": {
              "name": "status"
            }
          }
        },
        {
          "move": {
            "name": "return",
            "power": null,
            "type": {
              "name": "normal"
            },
            "category": {
              "name": "physical"
            }
          }
        },
        {
          "move": {
            "name": "frustration",
            "power": null,
            "type": {
              "name": "normal"
            },
            "category": {
              "name": "physical"
            }
          }
        },
        {
          "move": {
            "name": "hidden-power",
            "power": 60,
            "type": {
              "name": "normal"
            },
            "category": {
              "name": "special"
            }
          }
        },
        {
          "move": {
            "name": "rain-dance",
            "power": null,
            "type": {
              "name": "water"
            },
            "category": {
              "name": "status"
            }
          }
        },
        {
          "move": {
            "name": "sunny-day",
            "power": null,
            "type": {
              "name": "fire"
            },
            "category": {
              "name": "status"
            }
          }
        },
        {
          "move": {
            "name": "shadow-ball",
            "power": 80,
            "type": {
              "name": "ghost"
            },
            "category": {
              "name": "special"
            }
          }
        },
        {
          "move": {
            "name": "rock-smash",
            "power": 40,
            "type": {
              "name": "fighting"
            },
            "category": {
              "name": "physical"
            }
          }
        },
        {
          "move": {
            "name": "facade",
            "power": 70,
            "type": {
              "name": "normal"
            },
            "category": {
              "name": "physical"
            }
          }
        },
        {
          "move": {
            "name": "focus-punch",
            "power": 150,
            "type": {
              "name": "fighting"
            },
            "category": {
              "name": "physical"
            }
          }
        },
        {
          "move": {
            "name": "recycle",
            "power": null,
            "type": {
              "name": "normal"
            },
            "category": {
              "name": "status"
            }
          }
        },
        {
          "move": {
            "name": "brick-break",
            "power": 75,
            "type": {
              "name": "fighting"
            },
            "category": {
              "name": "physical"
            }
          }
        },
        {
          "move": {
            "name": "secret-power",
            "power": 70,
            "type": {
              "name": "normal"
            },
            "category": {
              "name": "physical"
            }
          }
        },
        {
          "move": {
            "name": "rock-tomb",
            "power": 60,
            "type": {
              "name": "rock"
            },
            "category": {
              "name": "physical"
            }
          }
        },
        {
          "move": {
            "name": "shock-wave",
            "power": 60,
            "type": {
              "name": "electric"
            },
            "category": {
              "name": "special"
            }
          }
        },
        {
          "move": {
            "name": "water-pulse",
            "power": 60,
            "type": {
              "name": "water"
            },
            "category": {
              "name": "special"
            }
          }
        },
        {
          "move": {
            "name": "natural-gift",
            "power": null,
            "type": {
              "name": "normal"
            },
            "category": {
              "name": "physical"
            }
          }
        },
        {
          "move": {
            "name": "fling",
            "power": null,
            "type": {
              "name": "dark"
            },
            "category": {
              "name": "physical"
            }
          }
        },
        {
          "move": {
            "name": "rock-climb",
            "power": 90,
            "type": {
              "name": "normal"
            },
            "category": {
              "name": "physical"
            }
          }
        },
        {
          "move": {
            "name": "captivate",
            "power": null,
            "type": {
              "name": "normal"
            },
            "category": {
              "name": "status"
            }
          }
        }
      ],
      "eggMoves": [
        {
          "move": {
            "name": "fire-punch",
            "power": 75,
            "type": {
              "name": "fire"
            },
            "category": {
              "name": "physical"
            }
          }
        },
        {
          "move": {
            "name": "ice-punch",
            "power": 75,
            "type": {
              "name": "ice"
            },
            "category": {
              "name": "physical"
            }
          }
        },
        {
          "move": {
            "name": "thunder-punch",
            "power": 75,
            "type": {
              "name": "electric"
            },
            "category": {
              "name": "physical"
            }
          }
        },
        {
          "move": {
            "name": "snore",
            "power": 50,
            "type": {
              "name": "normal"
            },
            "category": {
              "name": "special"
            }
          }
        },
        {
          "move": {
            "name": "mud-slap",
            "power": 20,
            "type": {
              "name": "ground"
            },
            "category": {
              "name": "special"
            }
          }
        },
        {
          "move": {
            "name": "icy-wind",
            "power": 55,
            "type": {
              "name": "ice"
            },
            "category": {
              "name": "special"
            }
          }
        },
        {
          "move": {
            "name": "rollout",
            "power": 30,
            "type": {
              "name": "rock"
            },
            "category": {
              "name": "physical"
            }
          }
        },
        {
          "move": {
            "name": "uproar",
            "power": 90,
            "type": {
              "name": "normal"
            },
            "category": {
              "name": "special"
            }
          }
        },
        {
          "move": {
            "name": "superpower",
            "power": 120,
            "type": {
              "name": "fighting"
            },
            "category": {
              "name": "physical"
            }
          }
        },
        {
          "move": {
            "name": "last-resort",
            "power": 140,
            "type": {
              "name": "normal"
            },
            "category": {
              "name": "physical"
            }
          }
        },
        {
          "move": {
            "name": "seed-bomb",
            "power": 80,
            "type": {
              "name": "grass"
            },
            "category": {
              "name": "physical"
            }
          }
        },
        {
          "move": {
            "name": "zen-headbutt",
            "power": 80,
            "type": {
              "name": "psychic"
            },
            "category": {
              "name": "physical"
            }
          }
        },
        {
          "move": {
            "name": "gunk-shot",
            "power": 120,
            "type": {
              "name": "poison"
            },
            "category": {
              "name": "physical"
            }
          }
        }
      ],
      "specy": {
        "evolution_chain": {
          "id": 72,
          "species": [
            {
              "name": "snorlax",
              "pre_evolution": 446,
              "evolution_condition": [
                {
                  "level": null,
                  "iq": 160,
                  "item": null,
                  "held_item": null,
                  "trigger": 1,
                  "time": ""
                }
              ]
            },
            {
              "name": "munchlax",
              "pre_evolution": null,
              "evolution_condition": []
            }
          ]
        },
        "category": [
          {
            "genus": "Big Eater Pokémon"
          }
        ]
      }
    }
  ]
}