{
  "pokemon": [
    {
      "name": "carnivine",
      "dex_id": 455,
      "weight": 270,
      "height": 14,
      "exp_yield": 159,
      "abilities": [
        {
          "ability": {
            "name": "levitate"
          }
        }
      ],
      "types": [
        {
          "type": {
            "name": "grass"
          }
        }
      ],
      "stats": [
        {
          "base_stat": 74,
          "stat": {
            "name": "hp"
          }
        },
        {
          "base_stat": 100,
          "stat": {
            "name": "attack"
          }
        },
        {
          "base_stat": 72,
          "stat": {
            "name": "defense"
          }
        },
        {
          "base_stat": 90,
          "stat": {
            "name": "special-attack"
          }
        },
        {
          "base_stat": 72,
          "stat": {
            "name": "special-defense"
          }
        },
        {
          "base_stat": 46,
          "stat": {
            "name": "speed"
          }
        }
      ],
      "levelUpMoves": [
        {
          "move": {
            "name": "bind",
            "power": 15,
            "type": {
              "name": "normal"
            },
            "category": {
              "name": "physical"
            }
          },
          "level": 1
        },
        {
          "move": {
            "name": "growth",
            "power": null,
            "type": {
              "name": "normal"
            },
            "category": {
              "name": "status"
            }
          },
          "level": 1
        },
        {
          "move": {
            "name": "bite",
            "power": 60,
            "type": {
              "name": "dark"
            },
            "category": {
              "name": "physical"
            }
          },
          "level": 7
        },
        {
          "move": {
            "name": "vine-whip",
            "power": 45,
            "type": {
              "name": "grass"
            },
            "category": {
              "name": "physical"
            }
          },
          "level": 11
        },
        {
          "move": {
            "name": "sweet-scent",
            "power": null,
            "type": {
              "name": "normal"
            },
            "category": {
              "name": "status"
            }
          },
          "level": 17
        },
        {
          "move": {
            "name": "ingrain",
            "power": null,
            "type": {
              "name": "grass"
            },
            "category": {
              "name": "status"
            }
          },
          "level": 21
        },
        {
          "move": {
            "name": "feint-attack",
            "power": 60,
            "type": {
              "name": "dark"
            },
            "category": {
              "name": "physical"
            }
          },
          "level": 27
        },
        {
          "move": {
            "name": "stockpile",
            "power": null,
            "type": {
              "name": "normal"
            },
            "category": {
              "name": "status"
            }
          },
          "level": 31
        },
        {
          "move": {
            "name": "spit-up",
            "power": null,
            "type": {
              "name": "normal"
            },
            "category": {
              "name": "special"
            }
          },
          "level": 31
        },
        {
          "move": {
            "name": "swallow",
            "power": null,
            "type": {
              "name": "normal"
            },
            "category": {
              "name": "status"
            }
          },
          "level": 31
        },
        {
          "move": {
            "name": "crunch",
            "power": 80,
            "type": {
              "name": "dark"
            },
            "category": {
              "name": "physical"
            }
          },
          "level": 37
        },
        {
          "move": {
            "name": "wring-out",
            "power": null,
            "type": {
              "name": "normal"
            },
            "category": {
              "name": "special"
            }
          },
          "level": 41
        },
        {
          "move": {
            "name": "power-whip",
            "power": 120,
            "type": {
              "name": "grass"
            },
            "category": {
              "name": "physical"
            }
          },
          "level": 47
        }
      ],
      "machineMoves": [
        {
          "move": {
            "name": "swords-dance",
            "power": null,
            "type": {
              "name": "normal"
            },
            "category": {
              "name": "status"
            }
          }
        },
        {
          "move": {
            "name": "cut",
            "power": 50,
            "type": {
              "name": "normal"
            },
            "category": {
              "name": "physical"
            }
          }
        },
        {
          "move": {
            "name": "hyper-beam",
            "power": 150,
            "type": {
              "name": "normal"
            },
            "category": {
              "name": "special"
            }
          }
        },
        {
          "move": {
            "name": "solar-beam",
            "power": 120,
            "type": {
              "name": "grass"
            },
            "category": {
              "name": "special"
            }
          }
        },
        {
          "move": {
            "name": "toxic",
            "power": null,
            "type": {
              "name": "poison"
            },
            "category": {
              "name": "status"
            }
          }
        },
        {
          "move": {
            "name": "double-team",
            "power": null,
            "type": {
              "name": "normal"
            },
            "category": {
              "name": "status"
            }
          }
        },
        {
          "move": {
            "name": "flash",
            "power": null,
            "type": {
              "name": "normal"
            },
            "category": {
              "name": "status"
            }
          }
        },
        {
          "move": {
            "name": "rest",
            "power": null,
            "type": {
              "name": "psychic"
            },
            "category": {
              "name": "status"
            }
          }
        },
        {
          "move": {
            "name": "substitute",
            "power": null,
            "type": {
              "name": "normal"
            },
            "category": {
              "name": "status"
            }
          }
        },
        {
          "move": {
            "name": "thief",
            "power": 60,
            "type": {
              "name": "dark"
            },
            "category": {
              "name": "physical"
            }
          }
        },
        {
          "move": {
            "name": "protect",
            "power": null,
            "type": {
              "name": "normal"
            },
            "category": {
              "name": "status"
            }
          }
        },
        {
          "move": {
            "name": "sludge-bomb",
            "power": 90,
            "type": {
              "name": "poison"
            },
            "category": {
              "name": "special"
            }
          }
        },
        {
          "move": {
            "name": "giga-drain",
            "power": 75,
            "type": {
              "name": "grass"
            },
            "category": {
              "name": "special"
            }
          }
        },
        {
          "move": {
            "name": "endure",
            "power": null,
            "type": {
              "name": "normal"
            },
            "category": {
              "name": "status"
            }
          }
        },
        {
          "move": {
            "name": "swagger",
            "power": null,
            "type": {
              "name": "normal"
            },
            "category": {
              "name": "status"
            }
          }
        },
        {
          "move": {
            "name": "attract",
            "power": null,
            "type": {
              "name": "normal"
            },
            "category": {
              "name": "status"
            }
          }
        },
        {
          "move": {
            "name": "sleep-talk",
            "power": null,
            "type": {
              "name": "normal"
            },
            "category": {
              "name": "status"
            }
          }
        },
        {
          "move": {
            "name": "return",
            "power": null,
            "type": {
              "name": "normal"
            },
            "category": {
              "name": "physical"
            }
          }
        },
        {
          "move": {
            "name": "frustration",
            "power": null,
            "type": {
              "name": "normal"
            },
            "category": {
              "name": "physical"
            }
          }
        },
        {
          "move": {
            "name": "hidden-power",
            "power": 60,
            "type": {
              "name": "normal"
            },
            "category": {
              "name": "special"
            }
          }
        },
        {
          "move": {
            "name": "sunny-day",
            "power": null,
            "type": {
              "name": "fire"
            },
            "category": {
              "name": "status"
            }
          }
        },
        {
          "move": {
            "name": "facade",
            "power": 70,
            "type": {
              "name": "normal"
            },
            "category": {
              "name": "physical"
            }
          }
        },
        {
          "move": {
            "name": "secret-power",
            "power": 70,
            "type": {
              "name": "normal"
            },
            "category": {
              "name": "physical"
            }
          }
        },
        {
          "move": {
            "name": "bullet-seed",
            "power": 25,
            "type": {
              "name": "grass"
            },
            "category": {
              "name": "physical"
            }
          }
        },
        {
          "move": {
            "name": "natural-gift",
            "power": null,
            "type": {
              "name": "normal"
            },
            "category": {
              "name": "physical"
            }
          }
        },
        {
          "move": {
            "name": "payback",
            "power": 50,
            "type": {
              "name": "dark"
            },
            "category": {
              "name": "physical"
            }
          }
        },
        {
          "move": {
            "name": "fling",
            "power": null,
            "type": {
              "name": "dark"
            },
            "category": {
              "name": "physical"
            }
          }
        },
        {
          "move": {
            "name": "energy-ball",
            "power": 90,
            "type": {
              "name": "grass"
            },
            "category": {
              "name": "special"
            }
          }
        },
        {
          "move": {
            "name": "giga-impact",
            "power": 150,
            "type": {
              "name": "normal"
            },
            "category": {
              "name": "physical"
            }
          }
        },
        {
          "move": {
            "name": "captivate",
            "power": null,
            "type": {
              "name": "normal"
            },
            "category": {
              "name": "status"
            }
          }
        },
        {
          "move": {
            "name": "grass-knot",
            "power": null,
            "type": {
              "name": "grass"
            },
            "category": {
              "name": "special"
            }
          }
        }
      ],
      "eggMoves": [
        {
          "move": {
            "name": "snore",
            "power": 50,
            "type": {
              "name": "normal"
            },
            "category": {
              "name": "special"
            }
          }
        },
        {
          "move": {
            "name": "mud-slap",
            "power": 20,
            "type": {
              "name": "ground"
            },
            "category": {
              "name": "special"
            }
          }
        },
        {
          "move": {
            "name": "fury-cutter",
            "power": 40,
            "type": {
              "name": "bug"
            },
            "category": {
              "name": "physical"
            }
          }
        },
        {
          "move": {
            "name": "synthesis",
            "power": null,
            "type": {
              "name": "grass"
            },
            "category": {
              "name": "status"
            }
          }
        },
        {
          "move": {
            "name": "knock-off",
            "power": 65,
            "type": {
              "name": "dark"
            },
            "category": {
              "name": "physical"
            }
          }
        },
        {
          "move": {
            "name": "gastro-acid",
            "power": null,
            "type": {
              "name": "poison"
            },
            "category": {
              "name": "status"
            }
          }
        },
        {
          "move": {
            "name": "seed-bomb",
            "power": 80,
            "type": {
              "name": "grass"
            },
            "category": {
              "name": "physical"
            }
          }
        }
      ],
      "specy": {
        "evolution_chain": {
          "id": 236,
          "species": [
            {
              "name": "carnivine",
              "pre_evolution": null,
              "evolution_condition": []
            }
          ]
        },
        "category": [
          {
            "genus": "Bug Catcher Pokémon"
          }
        ]
      }
    }
  ]
}